bin/__init__.py
bin/estimate_bank_size.py
bin/manifold_add_test_cbc_bank.py
bin/manifold_cbc_bank.py
bin/manifold_cbc_bank_constrain.py
bin/manifold_cbc_bank_create_mass_model.py
bin/manifold_cbc_bank_gstlal_banksplitter_compat.py
bin/manifold_cbc_bank_refine.py
bin/manifold_cbc_bank_salpeter_mass_model.py
bin/manifold_cbc_bank_to_xml.py
bin/manifold_cbc_bank_trim.py
bin/manifold_group_cbc_bank.py
bin/manifold_plot_cbc_bank.py
bin/manifold_plot_mass_model.py
bin/manifold_plot_test_cbc_bank.py
bin/manifold_print_cbc_bank.py
bin/manifold_split_cbc_bank.py
bin/manifold_test_cbc_bank.py
bin/spatial_match.py
bin/volume_element.py
gwsci_manifold-0.0.1.data/scripts/manifold_add_test_cbc_bank.py
gwsci_manifold-0.0.1.data/scripts/manifold_cbc_bank.py
gwsci_manifold-0.0.1.data/scripts/manifold_cbc_bank_refine.py
gwsci_manifold-0.0.1.data/scripts/manifold_cbc_bank_salpeter_mass_model.py
gwsci_manifold-0.0.1.data/scripts/manifold_cbc_bank_to_xml.py
gwsci_manifold-0.0.1.data/scripts/manifold_cbc_bank_trim.py
gwsci_manifold-0.0.1.data/scripts/manifold_plot_mass_model.py
gwsci_manifold-0.0.1.data/scripts/manifold_plot_test_cbc_bank.py
gwsci_manifold-0.0.1.data/scripts/manifold_test_cbc_bank.py
manifold/__init__.py
manifold/coordinate.py
manifold/cover.py
manifold/metric.py
manifold/signal.py
manifold/visual.py
manifold/sources/__init__.py
manifold/sources/cbc.py
manifold/sources/simple.py
manifold/utilities/__init__.py
manifold/utilities/common.py
manifold/utilities/data.py
manifold/utilities/quality.py
manifold/utilities/testing.py
gwsci_manifold-0.0.1.dist-info/LICENSE
gwsci_manifold-0.0.1.dist-info/METADATA
gwsci_manifold-0.0.1.dist-info/WHEEL
gwsci_manifold-0.0.1.dist-info/top_level.txt
gwsci_manifold-0.0.1.dist-info/RECORD
