Metadata-Version: 2.1
Name: gwsci-manifold
Version: 0.0.1
Summary: Geometric tools for gravitational wave data analysis
Home-page: https://git.ligo.org/chad-hanna/manifold
Author: Chad Hanna
Author-email: crh184@psu.edu
License: UNKNOWN
Platform: UNKNOWN
Classifier: Programming Language :: Python :: 3
Classifier: Operating System :: OS Independent
Requires-Python: >=3.6
License-File: LICENSE
